timing/__init__.py
timing/timing.py
timering-1.0.2.dist-info/LICENSE
timering-1.0.2.dist-info/METADATA
timering-1.0.2.dist-info/WHEEL
timering-1.0.2.dist-info/top_level.txt
timering-1.0.2.dist-info/RECORD
