Metadata-Version: 2.1
Name: timering
Version: 1.0.2
Summary: The only timing library you'll ever need.
Author: ruzickbelle
License: BSD 3-Clause License
Project-URL: Repository, https://github.com/ruzickbelle/python-timing
Project-URL: Changelog, https://github.com/ruzickbelle/python-timing/blob/main/CHANGELOG.md
Keywords: timer,timing
Classifier: License :: OSI Approved :: BSD License
Classifier: Programming Language :: Python
Classifier: Programming Language :: Python :: 3
Classifier: Programming Language :: Python :: 3.8
Classifier: Programming Language :: Python :: 3.9
Classifier: Programming Language :: Python :: 3.10
Classifier: Programming Language :: Python :: 3.11
Classifier: Programming Language :: Python :: 3.12
Requires-Python: >=3.8
License-File: LICENSE
Provides-Extra: build
Requires-Dist: setuptools ; extra == 'build'
Requires-Dist: wheel ; extra == 'build'
Requires-Dist: build ; extra == 'build'
Requires-Dist: twine ; extra == 'build'
Provides-Extra: dev
Requires-Dist: autopep8 ; extra == 'dev'
Requires-Dist: pylint ; extra == 'dev'
Requires-Dist: pytest ; extra == 'dev'
